{
  "updated_at": "2026-06-19 17:14:41",
  "headline": "見送り / 0株 / 約0.0円 / 仮想 2勝0敗 / 実弾まで残り89",
  "decision": "SKIP",
  "symbol": "1321.T",
  "price": 74630.0,
  "qty": 0,
  "amount": 0.0,
  "order_instruction": "なし",
  "shadow_account": {
    "is_running": true,
    "equity": 1007120.0,
    "cash": 1007120.0,
    "realized_pnl": 7120.0,
    "unrealized_yen": 0.0,
    "return_pct": 0.71,
    "position": "なし",
    "position_qty": 0,
    "entry_price": 0.0,
    "current_price": 74630.0,
    "closed_trades": 2,
    "wins": 2,
    "losses": 0,
    "win_rate": 100.0
  },
  "experience_count": 11,
  "experience_level": "BEGINNER",
  "readiness": {
    "updated_at": "2026-06-19 17:14:41",
    "experience_count": 11,
    "closed_trades": 2,
    "wins": 2,
    "losses": 0,
    "win_rate": 100.0,
    "realized_pnl": 7120.0,
    "unrealized_yen": 0.0,
    "shadow_equity": 1007120.0,
    "shadow_return_pct": 0.71,
    "remaining_to_shadow_review": 39,
    "remaining_to_real_review": 89,
    "shadow_review_ready": false,
    "real_review_ready": false,
    "multi_asset_experience_count": 0,
    "mode": "SHADOW_ONLY",
    "real_trade_allowed": false,
    "rules": [
      "実弾開始は最低100経験以上",
      "閉じたトレード20件以上",
      "PnL監査が正常",
      "最大DDと勝率確認後"
    ]
  },
  "strategy_5x10_decision": "SKIP",
  "strategy_5x10_votes": {
    "LONG": 11.83,
    "SHORT": 0.0,
    "SKIP": 14.3,
    "HOLD": 4.82
  },
  "exit_engine": {
    "time": "2026-06-19 17:14:40",
    "exit_now": true,
    "exit_reason": "TAKE_PROFIT",
    "side": "LONG",
    "entry_price": 72620.0,
    "current_price": 74630.0,
    "unrealized_pct": 2.768,
    "stop_pct": -0.01,
    "take_profit_pct": 0.022,
    "trail_pct": 0.012,
    "vol_mode": "DANGER"
  },
  "brain_status": "NO_GO",
  "brain_score": 80,
  "real_trade_allowed": false,
  "universe": "JP_ETF_ONLY",
  "allowed_assets": [
    "1321.T",
    "1306.T",
    "1475.T"
  ],
  "blocked_assets": [
    "BTC-USD",
    "USDJPY=X",
    "QQQ",
    "SOXX"
  ],
  "mode": "SHADOW_ONLY_CORE_5x10",
  "status": "OK"
}